Alexsecdemoraw.py
mymod1/__init__.py
mymod1/testmymod1.py
Bfixsecdemo-1.0.0.dist-info/METADATA
Bfixsecdemo-1.0.0.dist-info/WHEEL
Bfixsecdemo-1.0.0.dist-info/top_level.txt
Bfixsecdemo-1.0.0.dist-info/RECORD
