Metadata-Version: 2.1
Name: Bfixsecdemo
Version: 1.0.0
Summary: A sample Python project, do not download it!
Author: Bfix
Author-email: zhuzhuzhuzai@gmail.com
License: MIT
